openmairie.robotframework-4.11.10006-py3.12-nspkg.pth
openmairie/robotframework/__init__.py
openmairie/robotframework/formulaire.robot
openmairie/robotframework/menu.robot
openmairie/robotframework/module_gen.robot
openmairie/robotframework/module_import.robot
openmairie/robotframework/module_reqmo.robot
openmairie/robotframework/module_sig_interne.robot
openmairie/robotframework/navigation.robot
openmairie/robotframework/om_collectivite.robot
openmairie/robotframework/om_droit.robot
openmairie/robotframework/om_etat.robot
openmairie/robotframework/om_lettretype.robot
openmairie/robotframework/om_logo.robot
openmairie/robotframework/om_parametre.robot
openmairie/robotframework/om_profil.robot
openmairie/robotframework/om_requete.robot
openmairie/robotframework/om_resources.robot
openmairie/robotframework/om_sousetat.robot
openmairie/robotframework/om_utilisateur.robot
openmairie/robotframework/om_widget.robot
openmairie/robotframework/pdf.robot
openmairie/robotframework/tableau.robot
openmairie/robotframework/utils.robot
openmairie_robotframework-4.11.10006.dist-info/METADATA
openmairie_robotframework-4.11.10006.dist-info/WHEEL
openmairie_robotframework-4.11.10006.dist-info/namespace_packages.txt
openmairie_robotframework-4.11.10006.dist-info/top_level.txt
openmairie_robotframework-4.11.10006.dist-info/RECORD
