Metadata-Version: 2.4
Name: openmairie.robotframework
Version: 4.11.10006
Summary: RobotFramework Library for functional testing openMairie Framework based apps
Home-page: http://www.openmairie.org/framework
Author: openMairie
Author-email: contact@openmairie.org
License: GPL
Project-URL: Source, https://gitlab.com/openmairie/openmairie.robotframework/
Keywords: openMairie RobotFramework
Platform: any
Classifier: Programming Language :: Python
Classifier: License :: OSI Approved :: GNU General Public License (GPL)
Requires-Dist: setuptools
Dynamic: author
Dynamic: author-email
Dynamic: classifier
Dynamic: description
Dynamic: home-page
Dynamic: keywords
Dynamic: license
Dynamic: platform
Dynamic: project-url
Dynamic: requires-dist
Dynamic: summary
